odoo10_addon_sale_generator-10.0.1.0.1-py2.7-nspkg.pth
odoo/addons/sale_generator/README.rst
odoo/addons/sale_generator/__init__.py
odoo/addons/sale_generator/__manifest__.py
odoo/addons/sale_generator/data/data.xml
odoo/addons/sale_generator/i18n/fr.po
odoo/addons/sale_generator/models/__init__.py
odoo/addons/sale_generator/models/partner.py
odoo/addons/sale_generator/models/sale_generator.py
odoo/addons/sale_generator/models/sale_order.py
odoo/addons/sale_generator/security/ir.model.access.csv
odoo/addons/sale_generator/security/ir.rule.csv
odoo/addons/sale_generator/static/img/sale_gen_tmpl.png
odoo/addons/sale_generator/static/img/sale_generator.png
odoo/addons/sale_generator/tests/__init__.py
odoo/addons/sale_generator/tests/test_sale_generator.py
odoo/addons/sale_generator/views/generator_view.xml
odoo/addons/sale_generator/views/partner_view.xml
odoo/addons/sale_generator/views/sale_view.xml
odoo10_addon_sale_generator-10.0.1.0.1.dist-info/DESCRIPTION.rst
odoo10_addon_sale_generator-10.0.1.0.1.dist-info/METADATA
odoo10_addon_sale_generator-10.0.1.0.1.dist-info/RECORD
odoo10_addon_sale_generator-10.0.1.0.1.dist-info/WHEEL
odoo10_addon_sale_generator-10.0.1.0.1.dist-info/metadata.json
odoo10_addon_sale_generator-10.0.1.0.1.dist-info/namespace_packages.txt
odoo10_addon_sale_generator-10.0.1.0.1.dist-info/top_level.txt
